duster/__init__.py
duster-0.2.5.dist-info/DESCRIPTION.rst
duster-0.2.5.dist-info/METADATA
duster-0.2.5.dist-info/RECORD
duster-0.2.5.dist-info/WHEEL
duster-0.2.5.dist-info/metadata.json
duster-0.2.5.dist-info/pbr.json
duster-0.2.5.dist-info/top_level.txt
