Metadata-Version: 2.0
Name: duster
Version: 0.2.5
Summary: Reset IPython namespace and reload specified packages
Home-page: https://github.com/lebedov/duster/
Author: Lev Givon
Author-email: lev@columbia.edu
License: BSD
Platform: UNKNOWN
Classifier: Development Status :: 3 - Alpha
Classifier: Environment :: Console
Classifier: Framework :: IPython
Classifier: Intended Audience :: Developers
Classifier: License :: OSI Approved :: BSD License
Classifier: Operating System :: OS Independent
Classifier: Programming Language :: Python
Classifier: Topic :: Software Development
Requires-Dist: ipython (>=0.13)
Provides-Extra: numpy
Requires-Dist: numpy; extra == 'numpy'
